MANIFEST.in
README.md
requirements.txt
setup.py
django_lookup_table_rating_widget/__init__.py
django_lookup_table_rating_widget/widgets.py
django_lookup_table_rating_widget.egg-info/PKG-INFO
django_lookup_table_rating_widget.egg-info/SOURCES.txt
django_lookup_table_rating_widget.egg-info/dependency_links.txt
django_lookup_table_rating_widget.egg-info/not-zip-safe
django_lookup_table_rating_widget.egg-info/requires.txt
django_lookup_table_rating_widget.egg-info/top_level.txt
django_lookup_table_rating_widget/locale/zh_Hans/LC_MESSAGES/django.mo
django_lookup_table_rating_widget/locale/zh_Hans/LC_MESSAGES/django.po
django_lookup_table_rating_widget/migrations/__init__.py
django_lookup_table_rating_widget/static/django-lookup-table-rating-widget/css/django-lookup-table-rating-widget.css
django_lookup_table_rating_widget/static/django-lookup-table-rating-widget/js/django-lookup-table-rating-widget.js
django_lookup_table_rating_widget/templates/django-lookup-table-rating-widget/django-lookup-table-rating-widget.html